LICENSE
README.md
setup.py
calendric/__init__.py
calendric.egg-info/PKG-INFO
calendric.egg-info/SOURCES.txt
calendric.egg-info/dependency_links.txt
calendric.egg-info/top_level.txt